NovaForger/Message.py
NovaForger/__init__.py
NovaForger/chat_models.py
NovaForger/tools.py
NovaForger/utils.py
NovaForger-0.1.1.dist-info/LICENSE
NovaForger-0.1.1.dist-info/METADATA
NovaForger-0.1.1.dist-info/WHEEL
NovaForger-0.1.1.dist-info/top_level.txt
NovaForger-0.1.1.dist-info/RECORD
